Workbook

Sheet Cómo funciona
A1: Agenda de camiones · ejemplo de cómo la llena el agente
A2: Todos los datos de este archivo son FICTICIOS. Es una maqueta para conversar con Pato; el formato final se ajusta a su Excel real.
A4: Hoja | B4: Para qué sirve
A5: Agenda | B5: La agenda de Pato. Una fila por camión. El agente AGREGA filas al final de la tabla; Pato las confirma y puede escribir filas a mano.
A6: Cupo | B6: Cuántos camiones hay por día contra la capacidad. Marca COPADO. (El agente hace el mismo cálculo antes de escribir.)
A7: Registro | B7: Cada correo que leyó el agente y qué hizo con él (incluye cotizaciones, que no van a la agenda). Sirve para medir y revisar.
A9: Columna Estado | B9: Qué significa
A10: POR CONFIRMAR | B10: Lo escribe el agente: había cupo. Pato debe confirmar.
A11: CONFIRMADO | B11: Lo escribe Pato cuando confirma. El agente nunca lo escribe.
A12: URGENTE | B12: Lo escribe el agente: piden con menos de 2 días de anticipación. Llega alerta.
A13: SIN CUPO | B13: Lo escribe el agente: el día pedido ya estaba copado. Llega alerta con el próximo día con cupo.
A14: REVISAR | B14: Lo escribe el agente: no está seguro del tipo o la fecha. Llega alerta.
A15: CANCELADO | B15: Lo escribe el agente si el cliente cancela (o Pato a mano).
A17: Quién escribe qué
A18: El agente | B18: Fecha, Hora, Tipo, Cliente, Obra, N° cotización, Contacto, Transporte, Detalle, Estado, Origen, ID hilo.
A19: Pato | B19: Cambia Estado a CONFIRMADO, corrige lo que esté mal y agrega a mano lo que llegue por otro lado (Origen = 'Ingreso manual').
A21: Celdas a editar | B21: Hoja Cupo: celdas con fondo amarillo (capacidad por día y anticipación mínima). Son supuestos a validar con Pato.

Sheet Agenda
A1: Fecha | B1: Hora | C1: Tipo | D1: Cliente | E1: Obra | F1: N° cotización | G1: Contacto | H1: Transporte | I1: Detalle | J1: Estado | K1: Origen | L1: ID hilo
A2: 46314 | B2: 0.33333333 | C2: Recepción | D2: Constructora Cordillera | E2: Edificio Los Robles | F2: 4510 | G2: Contacto 1 · +56 9 0000 0000 | H2: Patente XX-YY-10 | I2: Devolución parcial | J2: CONFIRMADO | K2: Correo 15-10 08:10 · «Re: Cotización 4510» | L2: hilo-1001
A3: 46314 | B3: 0.35416667 | C3: Despacho | D3: Inmobiliaria Pacífico Sur | E3: Condominio Mirador | F3: 4511 | G3: Contacto 2 · +56 9 0000 0001 | I3: Andamio multidireccional | J3: CONFIRMADO | K3: Correo 15-10 09:11 · «Re: Cotización 4511» | L3: hilo-1002
A4: 46314 | B4: 0.375 | C4: Despacho | D4: Montajes del Valle | E4: Hospital Sector Norte | F4: 4512 | G4: Contacto 3 · +56 9 0000 0002 | H4: Patente XX-YY-12 | I4: Andamio multidireccional | J4: CONFIRMADO | K4: Correo 15-10 10:12 · «Re: Cotización 4512» | L4: hilo-1003
A5: 46314 | B5: 0.39583333 | C5: Recepción | D5: Edificaciones Maipo | E5: Colegio San Pedro | F5: 4513 | G5: Contacto 4 · +56 9 0000 0003 | I5: Devolución parcial | J5: CONFIRMADO | K5: Correo 15-10 11:13 · «Re: Cotización 4513» | L5: hilo-1004
A6: 46314 | B6: 0.41666667 | C6: Despacho | D6: Constructora Litoral | E6: Bodega Lampa Oriente | F6: 4514 | G6: Contacto 5 · +56 9 0000 0004 | H6: Patente XX-YY-14 | I6: Andamio multidireccional | J6: CONFIRMADO | K6: Ingreso manual (Pato)
A7: 46314 | B7: 0.4375 | C7: Despacho | D7: Obras Civiles Aconcagua | E7: Torre Centro | F7: 4515 | G7: Contacto 6 · +56 9 0000 0005 | I7: Andamio multidireccional | J7: CONFIRMADO | K7: Correo 15-10 13:15 · «Re: Cotización 4515» | L7: hilo-1006
A8: 46314 | B8: 0.45833333 | C8: Recepción | D8: Ingeniería Quilicura | E8: Planta Quilicura | F8: 4516 | G8: Contacto 7 · +56 9 0000 0006 | H8: Patente XX-YY-16 | I8: Devolución parcial | J8: CONFIRMADO | K8: Correo 15-10 14:16 · «Re: Cotización 4516» | L8: hilo-1007
A9: 46314 | B9: 0.47916667 | C9: Despacho | D9: Constructora Los Alerces | E9: Edificio Alerce | F9: 4517 | G9: Contacto 8 · +56 9 0000 0007 | I9: Andamio multidireccional | J9: POR CONFIRMAR | K9: Correo 15-10 15:17 · «Re: Cotización 4517» | L9: hilo-1008
A10: 46314 | B10: 0.5 | C10: Despacho | D10: Remodelaciones Ñuñoa | E10: Casa Ñuñoa | F10: 4518 | G10: Contacto 9 · +56 9 0000 0008 | H10: Patente XX-YY-18 | I10: Andamio multidireccional | J10: POR CONFIRMAR | K10: Correo 15-10 16:18 · «Re: Cotización 4518» | L10: hilo-1009
A11: 46314 | B11: 0.52083333 | C11: Recepción | D11: Constructora Altamira | E11: Mall Altamira (fachada) | F11: 4519 | G11: Contacto 10 · +56 9 0000 0009 | I11: Devolución parcial | J11: POR CONFIRMAR | K11: Correo 15-10 17:19 · «Re: Cotización 4519» | L11: hilo-1010
A12: 46314 | B12: Sin hora | C12: Despacho | D12: Constructora Precordillera | E12: Edificio Plaza Oriente | F12: 4533 | G12: Contacto 11 · +56 9 0000 0011 | I12: Pidió lunes 19. Día copado. Próximo día con cupo: mar 20-10. | J12: SIN CUPO | K12: Correo 16-10 10:05 · «Re: Cotización 4533» | L12: hilo-1011
A13: 46315 | B13: 0.375 | C13: Recepción | D13: Inmobiliaria Pacífico Sur | E13: Condominio Mirador | F13: 4511 | G13: Contacto 2 · +56 9 0000 0001 | H13: Patente XX-YY-21 | I13: Devuelven 40 verticales y 60 diagonales | J13: POR CONFIRMAR | K13: Correo 16-10 11:40 · «Devolución obra Mirador» | L13: hilo-1012
A14: 46315 | B14: 0.4375 | C14: Camión Alzatec | D14: Alzatec (interno) | E14: Galvanizadora | G14: Pato | H14: Camión Alzatec | I14: Retirar material galvanizado | J14: POR CONFIRMAR | K14: Correo 16-10 12:15 · «Retiro galvanizado» (interno) | L14: hilo-1013
A15: 46315 | B15: Sin hora | C15: Despacho | D15: Montajes del Valle | E15: Hospital Sector Norte | F15: 4512 | G15: Contacto 3 · +56 9 0000 0002 | I15: Cliente pidió 'el martes' y luego escribió 'no vamos a ir'. | J15: CANCELADO | K15: Correo 16-10 15:02 · «Re: Cotización 4512» | L15: hilo-1014
A16: 46316 | B16: 0.35416667 | C16: Despacho | D16: Constructora Los Alerces | E16: Edificio Alerce | F16: 4540 | G16: Contacto 12 · +56 9 0000 0012 | I16: Torre escala completa | J16: POR CONFIRMAR | K16: Correo 16-10 16:20 · «Re: Cotización 4540» (CC vendedor) | L16: hilo-1015
A17: 46311 | B17: Tarde | C17: Despacho | D17: Remodelaciones Ñuñoa | E17: Casa Ñuñoa | F17: 4541 | G17: Contacto 13 · +56 9 0000 0013 | I17: 'Lo voy a buscar hoy en la tarde' | J17: URGENTE | K17: Correo 16-10 09:03 · «Re: Cotización 4541» | L17: hilo-1016
C18: Recepción | D18: Constructora Altamira | E18: Mall Altamira (fachada) | F18: 4519 | G18: Contacto 10 · +56 9 0000 0009 | I18: Escribió 'la próxima semana devolvemos todo', sin día. | J18: REVISAR | K18: Correo 16-10 17:45 · «Fin de obra Altamira» | L18: hilo-1017

Sheet Cupo
A1: Cupo por día
A3: Capacidad máxima de camiones por día | B3: 10 | C3: Supuesto: gerencia dijo ~10 camiones diarios. Validar con Pato si hay máximo por día, por bloque o por tipo.
A4: Anticipación mínima (días) | B4: 2 | C4: Regla indicada por gerencia: agendar con 2 días de anticipación. Menos que eso → URGENTE.
A6: Fecha | B6: Camiones agendados | C6: Capacidad | D6: Cupos libres | E6: Estado del día | F6: Cuenta todas las filas de ese día menos SIN CUPO y CANCELADO (incluye las escritas a mano).
A7: 46311 | B7: =COUNTIFS(Agenda!$A:$A,A7)-COUNTIFS(Agenda!$A:$A,A7,Agenda!$J:$J,"SIN CUPO")-COUNTIFS(Agenda!$A:$A,A7,Agenda!$J:$J,"CANCELADO") -> 1 | C7: =$B$3 -> 10 | D7: =C7-B7 -> 9 | E7: =IF(B7>=C7,"COPADO","Con cupo") -> Con cupo
A8: 46314 | B8: =COUNTIFS(Agenda!$A:$A,A8)-COUNTIFS(Agenda!$A:$A,A8,Agenda!$J:$J,"SIN CUPO")-COUNTIFS(Agenda!$A:$A,A8,Agenda!$J:$J,"CANCELADO") -> 10 | C8: =$B$3 -> 10 | D8: =C8-B8 -> 0 | E8: =IF(B8>=C8,"COPADO","Con cupo") -> COPADO
A9: 46315 | B9: =COUNTIFS(Agenda!$A:$A,A9)-COUNTIFS(Agenda!$A:$A,A9,Agenda!$J:$J,"SIN CUPO")-COUNTIFS(Agenda!$A:$A,A9,Agenda!$J:$J,"CANCELADO") -> 2 | C9: =$B$3 -> 10 | D9: =C9-B9 -> 8 | E9: =IF(B9>=C9,"COPADO","Con cupo") -> Con cupo
A10: 46316 | B10: =COUNTIFS(Agenda!$A:$A,A10)-COUNTIFS(Agenda!$A:$A,A10,Agenda!$J:$J,"SIN CUPO")-COUNTIFS(Agenda!$A:$A,A10,Agenda!$J:$J,"CANCELADO") -> 1 | C10: =$B$3 -> 10 | D10: =C10-B10 -> 9 | E10: =IF(B10>=C10,"COPADO","Con cupo") -> Con cupo
A11: 46317 | B11: =COUNTIFS(Agenda!$A:$A,A11)-COUNTIFS(Agenda!$A:$A,A11,Agenda!$J:$J,"SIN CUPO")-COUNTIFS(Agenda!$A:$A,A11,Agenda!$J:$J,"CANCELADO") -> 0 | C11: =$B$3 -> 10 | D11: =C11-B11 -> 10 | E11: =IF(B11>=C11,"COPADO","Con cupo") -> Con cupo
A12: 46318 | B12: =COUNTIFS(Agenda!$A:$A,A12)-COUNTIFS(Agenda!$A:$A,A12,Agenda!$J:$J,"SIN CUPO")-COUNTIFS(Agenda!$A:$A,A12,Agenda!$J:$J,"CANCELADO") -> 0 | C12: =$B$3 -> 10 | D12: =C12-B12 -> 10 | E12: =IF(B12>=C12,"COPADO","Con cupo") -> Con cupo

Sheet Registro
A1: Recibido | B1: Asunto | C1: Clasificación | D1: Qué hizo el agente | E1: ID hilo
A2: 15-10 08:10 | B2: Re: Cotización 4510 | C2: Despacho | D2: Agregó fila lunes 19-10 08:00 (POR CONFIRMAR) | E2: hilo-1001
A3: 15-10 08:40 | B3: Cotización 4525 · Edificio Plaza | C3: Cotización | D3: Nada (no va a la agenda) | E3: hilo-1020
A4: 15-10 09:55 | B4: Consulta precios alzaprimas | C4: Cotización | D4: Nada (no va a la agenda) | E4: hilo-1021
A5: 16-10 09:03 | B5: Re: Cotización 4541 | C5: Despacho | D5: Agregó fila vie 16-10 (URGENTE) y envió alerta | E5: hilo-1016
A6: 16-10 10:05 | B6: Re: Cotización 4533 | C6: Despacho | D6: Lunes 19 copado: fila SIN CUPO, alerta con próximo día (mar 20-10) | E6: hilo-1011
A7: 16-10 11:40 | B7: Devolución obra Mirador | C7: Recepción | D7: Agregó fila mar 20-10 09:00 (POR CONFIRMAR) | E7: hilo-1012
A8: 16-10 12:15 | B8: Retiro galvanizado | C8: Camión Alzatec | D8: Agregó fila mar 20-10 10:30 (POR CONFIRMAR) | E8: hilo-1013
A9: 16-10 14:30 | B9: Re: Cotización 4512 | C9: Despacho | D9: Agregó fila mar 20-10 (POR CONFIRMAR) | E9: hilo-1014
A10: 16-10 15:02 | B10: Re: Cotización 4512 | C10: Cancelación | D10: Encontró la fila por ID hilo y la marcó CANCELADO | E10: hilo-1014
A11: 16-10 16:20 | B11: Re: Cotización 4540 (CC vendedor) | C11: Despacho | D11: Agregó fila mié 21-10 08:30 (POR CONFIRMAR) | E11: hilo-1015
A12: 16-10 16:25 | B12: Re: Cotización 4540 | C12: Despacho | D12: Mismo hilo y misma fecha: no duplicó la fila | E12: hilo-1015
A13: 16-10 17:45 | B13: Fin de obra Altamira | C13: Recepción | D13: Fecha poco clara: fila REVISAR y alerta | E13: hilo-1017
